{
  "commune": "La Tour-de-Peilz",
  "type": "proces_verbal",
  "year": "2023",
  "category": "proces-verbaux",
  "filename": "PV13-22-03-2023.pdf",
  "pv_number": 13,
  "session_date": "2023-03-22",
  "legislature": "2021-2026",
  "pdf_url": "https://www.la-tour-de-peilz.ch/doc_uploads/images/politique/conseil-communal/proces-verbaux/legislature_2021-2026/PV13-22-03-2023.pdf",
  "source_page": "https://www.la-tour-de-peilz.ch/politique/proces-verbaux.php",
  "pdf_path": "C:\\Users\\yannb\\Documents\\AI Riviera\\documents\\la-tour-de-peilz\\2023\\proces-verbaux\\PV13-22-03-2023.pdf",
  "text_path": "C:\\Users\\yannb\\Documents\\AI Riviera\\documents\\la-tour-de-peilz\\2023\\proces-verbaux\\PV13-22-03-2023.txt",
  "characters_extracted": 27325
}